[{"PlayerName":"M. Icardi","TeamName":"Galatasaray","Goals":"25","Penalties":"6","FirstGoals":"7"},{"PlayerName":"E. Džeko","TeamName":"Fenerbahce","Goals":"21","Penalties":"2","FirstGoals":"8"},{"PlayerName":"R. Manaj","TeamName":"Sivasspor","Goals":"18","Penalties":"4","FirstGoals":"12"},{"PlayerName":"M. Thiam","TeamName":"Pendikspor","Goals":"18","Penalties":"5","FirstGoals":"10"},{"PlayerName":"K. Piątek","TeamName":"Istanbul Basaksehir","Goals":"17","Penalties":"4","FirstGoals":"8"},{"PlayerName":"A. Buksa","TeamName":"Antalyaspor","Goals":"16","Penalties":"4","FirstGoals":"8"},{"PlayerName":"P. Onuachu","TeamName":"Trabzonspor","Goals":"15","Penalties":"0","FirstGoals":"7"},{"PlayerName":"Nuno da Costa","TeamName":"Kasımpaşa","Goals":"14","Penalties":"0","FirstGoals":"6"},{"PlayerName":"D. Drăguș","TeamName":"Gaziantep FK","Goals":"14","Penalties":"1","FirstGoals":"9"},{"PlayerName":"O. Aydın","TeamName":"Alanyaspor","Goals":"13","Penalties":"2","FirstGoals":"6"},{"PlayerName":"A. Kara","TeamName":"Kasımpaşa","Goals":"13","Penalties":"2","FirstGoals":"7"},{"PlayerName":"K. Aktürkoğlu","TeamName":"Galatasaray","Goals":"12","Penalties":"3","FirstGoals":"5"},{"PlayerName":"M. Batshuayi","TeamName":"Fenerbahce","Goals":"12","Penalties":"4","FirstGoals":"3"},{"PlayerName":"S. Çikalleshi","TeamName":"Konyaspor","Goals":"12","Penalties":"8","FirstGoals":"9"},{"PlayerName":"İ. Kahveci","TeamName":"Fenerbahce","Goals":"12","Penalties":"0","FirstGoals":"4"}]